upcache/__init__.py
upcache/cache.py
upcache/daemon.py
upcache/errors.py
upcache/helpers.py
upcache/networking.py
upcache/server.py
upcache/upcache.py
upcache/internal/__init__.py
upcache/internal/cache.py
upcache/internal/errors.py
upcache/internal/tcp.py
upcache-0.2.6.dist-info/METADATA
upcache-0.2.6.dist-info/WHEEL
upcache-0.2.6.dist-info/top_level.txt
upcache-0.2.6.dist-info/RECORD
