Metadata-Version: 2.1
Name: upcache
Version: 0.2.6
Summary: In-memory cache with multiprocessing support
Home-page: https://www.nuradius.com
Author: Nuradius Software
Author-email: todd@datacomponents.net
License: Apache Software License
Classifier: Development Status :: 3 - Alpha
Classifier: Intended Audience :: Developers
Classifier: License :: OSI Approved :: Apache Software License
Classifier: Programming Language :: Python
Classifier: Programming Language :: Python :: 3
Classifier: Programming Language :: Python :: 3.7
Classifier: Programming Language :: Python :: 3.8
Classifier: Programming Language :: Python :: 3.9
Classifier: Programming Language :: Python :: 3.10
Requires-Python: >=3.7
